devlake_mcp/__init__.py
devlake_mcp/__main__.py
devlake_mcp/cli.py
devlake_mcp/client.py
devlake_mcp/compat.py
devlake_mcp/config.py
devlake_mcp/constants.py
devlake_mcp/enums.py
devlake_mcp/error_reporter.py
devlake_mcp/generation_manager.py
devlake_mcp/git_utils.py
devlake_mcp/logging_config.py
devlake_mcp/retry_queue.py
devlake_mcp/server.py
devlake_mcp/session_manager.py
devlake_mcp/transcript_cache.py
devlake_mcp/transcript_scanner.py
devlake_mcp/utils.py
devlake_mcp/version_utils.py
devlake_mcp/hooks/__init__.py
devlake_mcp/hooks/hook_utils.py
devlake_mcp/hooks/post_tool_use.py
devlake_mcp/hooks/pre_tool_use.py
devlake_mcp/hooks/record_session.py
devlake_mcp/hooks/session_start.py
devlake_mcp/hooks/stop.py
devlake_mcp/hooks/transcript_utils.py
devlake_mcp/hooks/user_prompt_submit.py
devlake_mcp-0.4.7.dist-info/licenses/LICENSE
devlake_mcp-0.4.7.dist-info/METADATA
devlake_mcp-0.4.7.dist-info/WHEEL
devlake_mcp-0.4.7.dist-info/entry_points.txt
devlake_mcp-0.4.7.dist-info/top_level.txt
devlake_mcp-0.4.7.dist-info/RECORD
