Metadata-Version: 2.4
Name: devlake-mcp
Version: 0.4.7
Summary: AI programming data collection tool - supports Hooks (Claude Code/Cursor) and MCP server modes
Author-email: wangzhong <wangzhong@g7.com.cn>
License-Expression: MIT
Project-URL: Homepage, https://git.chinawayltd.com/engineering-efficiency/devlake-mcp
Project-URL: Repository, https://git.chinawayltd.com/engineering-efficiency/devlake-mcp
Project-URL: Issues, https://git.chinawayltd.com/engineering-efficiency/devlake-mcp
Keywords: mcp,devlake,model-context-protocol,ai,llm,claude-code,cursor,hooks,ai-programming,code-assistant
Classifier: Development Status :: 3 - Alpha
Classifier: Intended Audience :: Developers
Classifier: Programming Language :: Python :: 3
Classifier: Programming Language :: Python :: 3.9
Classifier: Programming Language :: Python :: 3.10
Classifier: Programming Language :: Python :: 3.11
Classifier: Programming Language :: Python :: 3.12
Classifier: Programming Language :: Python :: 3.13
Requires-Python: >=3.9
License-File: LICENSE
Requires-Dist: requests>=2.31.0
Provides-Extra: mcp
Requires-Dist: fastmcp~=2.13.0; python_version >= "3.10" and extra == "mcp"
Provides-Extra: full
Requires-Dist: devlake-mcp[mcp]; extra == "full"
Provides-Extra: dev
Requires-Dist: pytest>=7.0.0; extra == "dev"
Requires-Dist: pytest-asyncio>=0.21.0; extra == "dev"
Requires-Dist: pytest-cov>=4.1.0; extra == "dev"
Requires-Dist: pytest-mock>=3.12.0; extra == "dev"
Requires-Dist: pytest-timeout>=2.2.0; extra == "dev"
Requires-Dist: pytest-xdist>=3.5.0; extra == "dev"
Requires-Dist: responses>=0.24.0; extra == "dev"
Requires-Dist: freezegun>=1.4.0; extra == "dev"
Requires-Dist: black>=23.0.0; extra == "dev"
Requires-Dist: ruff>=0.1.0; extra == "dev"
Dynamic: license-file
